py34/Py34.py
py34/__init__.py
Py34-0.0.6.dist-info/LICENSE
Py34-0.0.6.dist-info/METADATA
Py34-0.0.6.dist-info/WHEEL
Py34-0.0.6.dist-info/top_level.txt
Py34-0.0.6.dist-info/RECORD
