Metadata-Version: 2.1
Name: Py34
Version: 0.0.6
Summary: A simple API to retrieve data from Rule34.xxx
Home-page: https://github.com/Wallkker/Py34API
Author: Wallkker
Author-email: 
License: UNKNOWN
Platform: UNKNOWN
Classifier: Programming Language :: Python :: 3
Classifier: License :: OSI Approved :: MIT License
Classifier: Operating System :: OS Independent
Requires-Python: >=3.5
